unearth-0.18.1.dist-info/METADATA
unearth-0.18.1.dist-info/WHEEL
unearth-0.18.1.dist-info/entry_points.txt
unearth-0.18.1.dist-info/licenses/LICENSE
unearth/__init__.py
unearth/__main__.py
unearth/auth.py
unearth/collector.py
unearth/errors.py
unearth/evaluator.py
unearth/fetchers/__init__.py
unearth/fetchers/legacy.py
unearth/fetchers/sync.py
unearth/finder.py
unearth/link.py
unearth/pep425tags.py
unearth/preparer.py
unearth/py.typed
unearth/session.py
unearth/utils.py
unearth/vcs/__init__.py
unearth/vcs/base.py
unearth/vcs/bazaar.py
unearth/vcs/git.py
unearth/vcs/hg.py
unearth/vcs/svn.py
unearth-0.18.1.dist-info/RECORD
